visorRobot/__init__.py
visorRobot/visor.py
visorRobot02-0.0.1.dist-info/METADATA
visorRobot02-0.0.1.dist-info/WHEEL
visorRobot02-0.0.1.dist-info/top_level.txt
visorRobot02-0.0.1.dist-info/RECORD
