Metadata-Version: 2.1
Name: visorRobot02
Version: 0.0.1
Summary: This is a vision feature created by kais
Author: misil han
Author-email: coko980715@gmail.com
Classifier: Programming Language :: Python :: 3
Requires-Python: >=3.6
